fintech/__init__.py
fintech/datev.py
fintech/ebics.py
fintech/external_code_sets.py
fintech/iban.py
fintech/rpc.py
fintech/sepa.py
fintech/swift.py
fintech/data/bankcodes.txt
fintech/data/scl.csv
fintech-7.9.0.dist-info/licenses/LICENSE.txt
fintech-7.9.0.dist-info/METADATA
fintech-7.9.0.dist-info/WHEEL
fintech-7.9.0.dist-info/entry_points.txt
fintech-7.9.0.dist-info/top_level.txt
fintech-7.9.0.dist-info/RECORD
