Metadata-Version: 2.4
Name: fintech
Version: 7.9.0
Summary: The Python Fintech package (SEPA, EBICS & more)
Home-page: https://www.joonis.de/fintech/
Author: Thimo Kraemer
Author-email: thimo.kraemer@joonis.de
License: https://www.joonis.de/fintech/license
Keywords: fintech,ebics,sepa,swift,mt940,camt,pain,iban,datev
Classifier: Topic :: Office/Business :: Financial
Classifier: Topic :: Office/Business :: Financial :: Accounting
Classifier: Intended Audience :: Developers
Classifier: Operating System :: POSIX :: Linux
Classifier: Operating System :: Microsoft :: Windows
Classifier: Operating System :: MacOS :: MacOS X
Classifier: Operating System :: POSIX :: BSD :: FreeBSD
Classifier: Programming Language :: Python :: 3
Classifier: Programming Language :: Python :: Implementation :: CPython
Classifier: License :: Free To Use But Restricted
Requires-Python: >=3.7, <3.15
License-File: LICENSE.txt
Requires-Dist: lxml
Requires-Dist: cryptography>=1.6
Requires-Dist: certifi
Requires-Dist: fpdf2<2.9,>=2.5.2
Requires-Dist: defusedxml
Dynamic: author
Dynamic: author-email
Dynamic: classifier
Dynamic: description
Dynamic: home-page
Dynamic: keywords
Dynamic: license
Dynamic: license-file
Dynamic: requires-dist
Dynamic: requires-python
Dynamic: summary
